cutilib/__init__.py
cutilib/fm.py
cutilib/matplotlib.py
cutilib/tensorboard.py
cutilib/wandb.py
cutipy/__init__.py
cutipy/debug.py
cutipy/deepdict.py
cutipy/designpatterns.py
cutipy/exp.py
cutipy/log.py
cutipy/putils.py
cutipy/thread.py
cutipy/tracking.py
cutix/__init__.py
cutix/prob.py
common_utils_anirbanl-0.3.1.dist-info/LICENSE
common_utils_anirbanl-0.3.1.dist-info/METADATA
common_utils_anirbanl-0.3.1.dist-info/WHEEL
common_utils_anirbanl-0.3.1.dist-info/top_level.txt
common_utils_anirbanl-0.3.1.dist-info/zip-safe
common_utils_anirbanl-0.3.1.dist-info/RECORD
