Metadata-Version: 2.1
Name: common-utils-anirbanl
Version: 0.3.1
Summary: Common python utils used by Anirban
Home-page: https://github.com/anirbanl/myutils
Author: Anirban Laha
Author-email: anirbanlaha@gmail.com
License: UNKNOWN
Project-URL: My Webpage, https://anirbanl.github.io/
Platform: UNKNOWN
Classifier: Intended Audience :: Education
Classifier: Intended Audience :: Science/Research
Classifier: Programming Language :: Python :: 3
Classifier: License :: OSI Approved :: MIT License
Classifier: Operating System :: OS Independent
Classifier: Topic :: Scientific/Engineering
Classifier: Topic :: Scientific/Engineering :: Artificial Intelligence
Requires-Python: >=3.6
License-File: LICENSE
Requires-Dist: attrs
Requires-Dist: tqdm
Requires-Dist: profilehooks
Requires-Dist: wandb
Requires-Dist: matplotlib
Requires-Dist: numpy
Requires-Dist: scipy
Requires-Dist: pandas
Requires-Dist: seaborn
